senaps_sensor/__init__.py
senaps_sensor/api.py
senaps_sensor/auth.py
senaps_sensor/binder.py
senaps_sensor/const.py
senaps_sensor/error.py
senaps_sensor/models.py
senaps_sensor/parsers.py
senaps_sensor/utils.py
senaps_sensor/vocabulary.py
senaps_sensor-2.16.0.dist-info/METADATA
senaps_sensor-2.16.0.dist-info/WHEEL
senaps_sensor-2.16.0.dist-info/licenses/LICENSE
senaps_sensor-2.16.0.dist-info/RECORD
