Metadata-Version: 2.3
Name: senaps_sensor
Version: 2.16.0
Summary: Senaps Sensor Data API Client
Author-email: CSIRO Data61 <senaps@csiro.au>
License: MIT License
Keywords: api,client,library,senaps,sensor
Classifier: Development Status :: 4 - Beta
Classifier: License :: OSI Approved :: MIT License
Classifier: Operating System :: OS Independent
Classifier: Programming Language :: Python
Classifier: Programming Language :: Python :: 2
Classifier: Programming Language :: Python :: 2.7
Classifier: Programming Language :: Python :: 3
Classifier: Programming Language :: Python :: 3.4
Classifier: Topic :: Software Development :: Libraries
Requires-Python: >=2.7
Requires-Dist: enum34; python_version < '3.4.0'
Requires-Dist: requests<3.0.0,>=2.22.0
Requires-Dist: six>=1.7.3
Provides-Extra: pandas
Requires-Dist: pandas<=0.25.3,>=0.18.1; extra == 'pandas'
